{
  "meta": {
    "date": "2026-03-27",
    "date_display": "Vr 27 mrt",
    "generated_at": "2026-03-28T05:33:13.905058+00:00",
    "gen_time": "06:33",
    "gameday": 2,
    "season": 2026
  },
  "briefing": "Geen briefing beschikbaar.",
  "teams": {
    "nym": {
      "abbr": "NYM",
      "result": null,
      "score": null,
      "opponent": null,
      "home": null,
      "record": "1-0",
      "starter": {
        "name": null,
        "line": null
      },
      "key_play": null,
      "next_game": {
        "date": "2026-03-28",
        "date_display": "",
        "vs": "PIT",
        "home": true,
        "starter": "David Peterson",
        "opp_starter": "Mitch Keller",
        "game_time_et": "16:10",
        "game_time_cet": "21:10"
      },
      "color": "#FF5910"
    },
    "tb": {
      "abbr": "TB",
      "result": null,
      "score": null,
      "opponent": null,
      "home": null,
      "record": "0-1",
      "starter": {
        "name": null,
        "line": null
      },
      "key_play": null,
      "next_game": {
        "date": "2026-03-28",
        "date_display": "",
        "vs": "STL",
        "home": false,
        "starter": "Joe Boyle",
        "opp_starter": "Michael McGreevy",
        "game_time_et": "14:15",
        "game_time_cet": "19:15"
      },
      "color": "#8FBCE6"
    }
  },
  "scores": [
    {
      "away": "NYY",
      "home": "SF",
      "away_score": 3,
      "home_score": 0,
      "status": "Final",
      "note": ""
    },
    {
      "away": "ATH",
      "home": "TOR",
      "away_score": 2,
      "home_score": 3,
      "status": "Final",
      "note": ""
    },
    {
      "away": "COL",
      "home": "MIA",
      "away_score": 1,
      "home_score": 2,
      "status": "Final",
      "note": ""
    },
    {
      "away": "KC",
      "home": "ATL",
      "away_score": 0,
      "home_score": 6,
      "status": "Final",
      "note": ""
    },
    {
      "away": "LAA",
      "home": "HOU",
      "away_score": 6,
      "home_score": 2,
      "status": "Final",
      "note": ""
    },
    {
      "away": "DET",
      "home": "SD",
      "away_score": 5,
      "home_score": 2,
      "status": "Final",
      "note": ""
    },
    {
      "away": "CLE",
      "home": "SEA",
      "away_score": 1,
      "home_score": 5,
      "status": "Final",
      "note": ""
    },
    {
      "away": "AZ",
      "home": "LAD",
      "away_score": 4,
      "home_score": 5,
      "status": "Final",
      "note": ""
    }
  ],
  "standings": {
    "al_east": [
      {
        "team": "NYY",
        "w": 2,
        "l": 0,
        "pct": "1.000",
        "gb": "—",
        "streak": "W2",
        "l10": "2-0"
      },
      {
        "team": "TOR",
        "w": 1,
        "l": 0,
        "pct": "1.000",
        "gb": "0.5",
        "streak": "W1",
        "l10": "1-0"
      },
      {
        "team": "BAL",
        "w": 1,
        "l": 0,
        "pct": "1.000",
        "gb": "0.5",
        "streak": "W1",
        "l10": "1-0"
      },
      {
        "team": "BOS",
        "w": 1,
        "l": 0,
        "pct": "1.000",
        "gb": "0.5",
        "streak": "W1",
        "l10": "1-0"
      },
      {
        "team": "TB",
        "w": 0,
        "l": 1,
        "pct": ".000",
        "gb": "1.5",
        "streak": "L1",
        "l10": "0-1"
      }
    ],
    "nl_east": [
      {
        "team": "MIA",
        "w": 1,
        "l": 0,
        "pct": "1.000",
        "gb": "—",
        "streak": "W1",
        "l10": "1-0"
      },
      {
        "team": "NYM",
        "w": 1,
        "l": 0,
        "pct": "1.000",
        "gb": "—",
        "streak": "W1",
        "l10": "1-0"
      },
      {
        "team": "WSH",
        "w": 1,
        "l": 0,
        "pct": "1.000",
        "gb": "—",
        "streak": "W1",
        "l10": "1-0"
      },
      {
        "team": "ATL",
        "w": 1,
        "l": 0,
        "pct": "1.000",
        "gb": "—",
        "streak": "W1",
        "l10": "1-0"
      },
      {
        "team": "PHI",
        "w": 1,
        "l": 0,
        "pct": "1.000",
        "gb": "—",
        "streak": "W1",
        "l10": "1-0"
      }
    ]
  },
  "watch": [
    {
      "away": "TB",
      "home": "STL",
      "game_time_et": "14:15",
      "game_time_cet": "19:15",
      "date": "2026-03-28",
      "date_display": "za 28 mrt",
      "starter_away": "Joe Boyle",
      "starter_home": "Michael McGreevy",
      "watch_status": "kijkbaar",
      "is_mine": true,
      "my_team": "TB"
    },
    {
      "away": "WSH",
      "home": "CHC",
      "game_time_et": "14:20",
      "game_time_cet": "19:20",
      "date": "2026-03-28",
      "date_display": "za 28 mrt",
      "starter_away": "Miles Mikolas",
      "starter_home": "Cade Horton",
      "watch_status": "kijkbaar",
      "is_mine": false,
      "my_team": null
    },
    {
      "away": "ATH",
      "home": "TOR",
      "game_time_et": "15:07",
      "game_time_cet": "20:07",
      "date": "2026-03-28",
      "date_display": "za 28 mrt",
      "starter_away": "Jeffrey Springs",
      "starter_home": "Dylan Cease",
      "watch_status": "kijkbaar",
      "is_mine": false,
      "my_team": null
    },
    {
      "away": "MIN",
      "home": "BAL",
      "game_time_et": "16:05",
      "game_time_cet": "21:05",
      "date": "2026-03-28",
      "date_display": "za 28 mrt",
      "starter_away": "Taj Bradley",
      "starter_home": "Kyle Bradish",
      "watch_status": "twijfel",
      "is_mine": false,
      "my_team": null
    },
    {
      "away": "TEX",
      "home": "PHI",
      "game_time_et": "16:05",
      "game_time_cet": "21:05",
      "date": "2026-03-28",
      "date_display": "za 28 mrt",
      "starter_away": "Jacob deGrom",
      "starter_home": "Aaron Nola",
      "watch_status": "twijfel",
      "is_mine": false,
      "my_team": null
    },
    {
      "away": "BOS",
      "home": "CIN",
      "game_time_et": "16:10",
      "game_time_cet": "21:10",
      "date": "2026-03-28",
      "date_display": "za 28 mrt",
      "starter_away": "Sonny Gray",
      "starter_home": "Brady Singer",
      "watch_status": "twijfel",
      "is_mine": false,
      "my_team": null
    },
    {
      "away": "PIT",
      "home": "NYM",
      "game_time_et": "16:10",
      "game_time_cet": "21:10",
      "date": "2026-03-28",
      "date_display": "za 28 mrt",
      "starter_away": "Mitch Keller",
      "starter_home": "David Peterson",
      "watch_status": "twijfel",
      "is_mine": true,
      "my_team": "NYM"
    },
    {
      "away": "COL",
      "home": "MIA",
      "game_time_et": "16:10",
      "game_time_cet": "21:10",
      "date": "2026-03-28",
      "date_display": "za 28 mrt",
      "starter_away": "Michael Lorenzen",
      "starter_home": "Eury Pérez",
      "watch_status": "twijfel",
      "is_mine": false,
      "my_team": null
    },
    {
      "away": "LAA",
      "home": "HOU",
      "game_time_et": "19:10",
      "game_time_cet": "00:10",
      "date": "2026-03-28",
      "date_display": "zo 29 mrt",
      "starter_away": "Reid Detmers",
      "starter_home": "Cristian Javier",
      "watch_status": "nacht",
      "is_mine": false,
      "my_team": null
    },
    {
      "away": "CWS",
      "home": "MIL",
      "game_time_et": "19:10",
      "game_time_cet": "00:10",
      "date": "2026-03-28",
      "date_display": "zo 29 mrt",
      "starter_away": "Sean Burke",
      "starter_home": "Chad Patrick",
      "watch_status": "nacht",
      "is_mine": false,
      "my_team": null
    },
    {
      "away": "KC",
      "home": "ATL",
      "game_time_et": "19:15",
      "game_time_cet": "00:15",
      "date": "2026-03-28",
      "date_display": "zo 29 mrt",
      "starter_away": "Michael Wacha",
      "starter_home": "Reynaldo López",
      "watch_status": "nacht",
      "is_mine": false,
      "my_team": null
    },
    {
      "away": "NYY",
      "home": "SF",
      "game_time_et": "19:15",
      "game_time_cet": "00:15",
      "date": "2026-03-28",
      "date_display": "zo 29 mrt",
      "starter_away": "Will Warren",
      "starter_home": "Tyler Mahle",
      "watch_status": "nacht",
      "is_mine": false,
      "my_team": null
    },
    {
      "away": "DET",
      "home": "SD",
      "game_time_et": "20:40",
      "game_time_cet": "01:40",
      "date": "2026-03-28",
      "date_display": "zo 29 mrt",
      "starter_away": "Jack Flaherty",
      "starter_home": "Randy Vásquez",
      "watch_status": "nacht",
      "is_mine": false,
      "my_team": null
    },
    {
      "away": "AZ",
      "home": "LAD",
      "game_time_et": "21:10",
      "game_time_cet": "03:10",
      "date": "2026-03-28",
      "date_display": "zo 29 mrt",
      "starter_away": "Eduardo Rodriguez",
      "starter_home": "Tyler Glasnow",
      "watch_status": "nacht",
      "is_mine": false,
      "my_team": null
    },
    {
      "away": "CLE",
      "home": "SEA",
      "game_time_et": "21:40",
      "game_time_cet": "03:40",
      "date": "2026-03-28",
      "date_display": "zo 29 mrt",
      "starter_away": "Joey Cantillo",
      "starter_home": "Bryan Woo",
      "watch_status": "nacht",
      "is_mine": false,
      "my_team": null
    },
    {
      "away": "MIN",
      "home": "BAL",
      "game_time_et": "13:35",
      "game_time_cet": "19:35",
      "date": "2026-03-29",
      "date_display": "zo 29 mrt",
      "starter_away": "Bailey Ober",
      "starter_home": "Shane Baz",
      "watch_status": "kijkbaar",
      "is_mine": false,
      "my_team": null
    },
    {
      "away": "TEX",
      "home": "PHI",
      "game_time_et": "13:35",
      "game_time_cet": "19:35",
      "date": "2026-03-29",
      "date_display": "zo 29 mrt",
      "starter_away": "MacKenzie Gore",
      "starter_home": "Jesús Luzardo",
      "watch_status": "kijkbaar",
      "is_mine": false,
      "my_team": null
    },
    {
      "away": "KC",
      "home": "ATL",
      "game_time_et": "13:35",
      "game_time_cet": "19:35",
      "date": "2026-03-29",
      "date_display": "zo 29 mrt",
      "starter_away": "Seth Lugo",
      "starter_home": "Grant Holmes",
      "watch_status": "kijkbaar",
      "is_mine": false,
      "my_team": null
    },
    {
      "away": "ATH",
      "home": "TOR",
      "game_time_et": "13:37",
      "game_time_cet": "19:37",
      "date": "2026-03-29",
      "date_display": "zo 29 mrt",
      "starter_away": "Luis Morales",
      "starter_home": "Eric Lauer",
      "watch_status": "kijkbaar",
      "is_mine": false,
      "my_team": null
    },
    {
      "away": "BOS",
      "home": "CIN",
      "game_time_et": "13:40",
      "game_time_cet": "19:40",
      "date": "2026-03-29",
      "date_display": "zo 29 mrt",
      "starter_away": "Connelly Early",
      "starter_home": "Rhett Lowder",
      "watch_status": "kijkbaar",
      "is_mine": false,
      "my_team": null
    },
    {
      "away": "PIT",
      "home": "NYM",
      "game_time_et": "13:40",
      "game_time_cet": "19:40",
      "date": "2026-03-29",
      "date_display": "zo 29 mrt",
      "starter_away": "Carmen Mlodzinski",
      "starter_home": "Nolan McLean",
      "watch_status": "kijkbaar",
      "is_mine": true,
      "my_team": "NYM"
    },
    {
      "away": "COL",
      "home": "MIA",
      "game_time_et": "13:40",
      "game_time_cet": "19:40",
      "date": "2026-03-29",
      "date_display": "zo 29 mrt",
      "starter_away": "Jose Quintana",
      "starter_home": "Max Meyer",
      "watch_status": "kijkbaar",
      "is_mine": false,
      "my_team": null
    },
    {
      "away": "LAA",
      "home": "HOU",
      "game_time_et": "14:10",
      "game_time_cet": "20:10",
      "date": "2026-03-29",
      "date_display": "zo 29 mrt",
      "starter_away": "Jack Kochanowicz",
      "starter_home": "Tatsuya Imai",
      "watch_status": "kijkbaar",
      "is_mine": false,
      "my_team": null
    },
    {
      "away": "CWS",
      "home": "MIL",
      "game_time_et": "14:10",
      "game_time_cet": "20:10",
      "date": "2026-03-29",
      "date_display": "zo 29 mrt",
      "starter_away": "Anthony Kay",
      "starter_home": "Brandon Sproat",
      "watch_status": "kijkbaar",
      "is_mine": false,
      "my_team": null
    },
    {
      "away": "TB",
      "home": "STL",
      "game_time_et": "14:15",
      "game_time_cet": "20:15",
      "date": "2026-03-29",
      "date_display": "zo 29 mrt",
      "starter_away": "Steven Matz",
      "starter_home": "Dustin May",
      "watch_status": "kijkbaar",
      "is_mine": true,
      "my_team": "TB"
    },
    {
      "away": "WSH",
      "home": "CHC",
      "game_time_et": "14:20",
      "game_time_cet": "20:20",
      "date": "2026-03-29",
      "date_display": "zo 29 mrt",
      "starter_away": "Jake Irvin",
      "starter_home": "Shota Imanaga",
      "watch_status": "kijkbaar",
      "is_mine": false,
      "my_team": null
    },
    {
      "away": "CLE",
      "home": "SEA",
      "game_time_et": "19:20",
      "game_time_cet": "01:20",
      "date": "2026-03-29",
      "date_display": "ma 30 mrt",
      "starter_away": "Slade Cecconi",
      "starter_home": "Emerson Hancock",
      "watch_status": "nacht",
      "is_mine": false,
      "my_team": null
    },
    {
      "away": "MIN",
      "home": "KC",
      "game_time_et": "16:10",
      "game_time_cet": "22:10",
      "date": "2026-03-30",
      "date_display": "ma 30 mrt",
      "starter_away": "TBD",
      "starter_home": "Kris Bubic",
      "watch_status": "nacht",
      "is_mine": false,
      "my_team": null
    },
    {
      "away": "TEX",
      "home": "BAL",
      "game_time_et": "18:35",
      "game_time_cet": "00:35",
      "date": "2026-03-30",
      "date_display": "di 31 mrt",
      "starter_away": "Jack Leiter",
      "starter_home": "Chris Bassitt",
      "watch_status": "nacht",
      "is_mine": false,
      "my_team": null
    },
    {
      "away": "PIT",
      "home": "CIN",
      "game_time_et": "18:40",
      "game_time_cet": "00:40",
      "date": "2026-03-30",
      "date_display": "di 31 mrt",
      "starter_away": "Braxton Ashcraft",
      "starter_home": "Chase Burns",
      "watch_status": "nacht",
      "is_mine": false,
      "my_team": null
    },
    {
      "away": "WSH",
      "home": "PHI",
      "game_time_et": "18:40",
      "game_time_cet": "00:40",
      "date": "2026-03-30",
      "date_display": "di 31 mrt",
      "starter_away": "TBD",
      "starter_home": "Taijuan Walker",
      "watch_status": "nacht",
      "is_mine": false,
      "my_team": null
    },
    {
      "away": "CWS",
      "home": "MIA",
      "game_time_et": "18:40",
      "game_time_cet": "00:40",
      "date": "2026-03-30",
      "date_display": "di 31 mrt",
      "starter_away": "Davis Martin",
      "starter_home": "Chris Paddack",
      "watch_status": "nacht",
      "is_mine": false,
      "my_team": null
    },
    {
      "away": "COL",
      "home": "TOR",
      "game_time_et": "19:07",
      "game_time_cet": "01:07",
      "date": "2026-03-30",
      "date_display": "di 31 mrt",
      "starter_away": "TBD",
      "starter_home": "Cody Ponce",
      "watch_status": "nacht",
      "is_mine": false,
      "my_team": null
    },
    {
      "away": "ATH",
      "home": "ATL",
      "game_time_et": "19:15",
      "game_time_cet": "01:15",
      "date": "2026-03-30",
      "date_display": "di 31 mrt",
      "starter_away": "TBD",
      "starter_home": "Bryce Elder",
      "watch_status": "nacht",
      "is_mine": false,
      "my_team": null
    },
    {
      "away": "LAA",
      "home": "CHC",
      "game_time_et": "19:40",
      "game_time_cet": "01:40",
      "date": "2026-03-30",
      "date_display": "di 31 mrt",
      "starter_away": "TBD",
      "starter_home": "TBD",
      "watch_status": "nacht",
      "is_mine": false,
      "my_team": null
    },
    {
      "away": "TB",
      "home": "MIL",
      "game_time_et": "19:40",
      "game_time_cet": "01:40",
      "date": "2026-03-30",
      "date_display": "di 31 mrt",
      "starter_away": "Nick Martinez",
      "starter_home": "Kyle Harrison",
      "watch_status": "nacht",
      "is_mine": true,
      "my_team": "TB"
    },
    {
      "away": "NYM",
      "home": "STL",
      "game_time_et": "19:45",
      "game_time_cet": "01:45",
      "date": "2026-03-30",
      "date_display": "di 31 mrt",
      "starter_away": "Clay Holmes",
      "starter_home": "Kyle Leahy",
      "watch_status": "nacht",
      "is_mine": true,
      "my_team": "NYM"
    },
    {
      "away": "BOS",
      "home": "HOU",
      "game_time_et": "20:10",
      "game_time_cet": "02:10",
      "date": "2026-03-30",
      "date_display": "di 31 mrt",
      "starter_away": "Ranger Suarez",
      "starter_home": "Lance McCullers Jr.",
      "watch_status": "nacht",
      "is_mine": false,
      "my_team": null
    },
    {
      "away": "SF",
      "home": "SD",
      "game_time_et": "21:40",
      "game_time_cet": "03:40",
      "date": "2026-03-30",
      "date_display": "di 31 mrt",
      "starter_away": "TBD",
      "starter_home": "Walker Buehler",
      "watch_status": "nacht",
      "is_mine": false,
      "my_team": null
    },
    {
      "away": "NYY",
      "home": "SEA",
      "game_time_et": "21:40",
      "game_time_cet": "03:40",
      "date": "2026-03-30",
      "date_display": "di 31 mrt",
      "starter_away": "Ryan Weathers",
      "starter_home": "Luis Castillo",
      "watch_status": "nacht",
      "is_mine": false,
      "my_team": null
    },
    {
      "away": "DET",
      "home": "AZ",
      "game_time_et": "22:10",
      "game_time_cet": "04:10",
      "date": "2026-03-30",
      "date_display": "di 31 mrt",
      "starter_away": "Justin Verlander",
      "starter_home": "Michael Soroka",
      "watch_status": "nacht",
      "is_mine": false,
      "my_team": null
    },
    {
      "away": "CLE",
      "home": "LAD",
      "game_time_et": "22:10",
      "game_time_cet": "04:10",
      "date": "2026-03-30",
      "date_display": "di 31 mrt",
      "starter_away": "Parker Messick",
      "starter_home": "Roki Sasaki",
      "watch_status": "nacht",
      "is_mine": false,
      "my_team": null
    },
    {
      "away": "TEX",
      "home": "BAL",
      "game_time_et": "18:35",
      "game_time_cet": "00:35",
      "date": "2026-03-31",
      "date_display": "wo 1 apr",
      "starter_away": "TBD",
      "starter_home": "Zach Eflin",
      "watch_status": "nacht",
      "is_mine": false,
      "my_team": null
    },
    {
      "away": "PIT",
      "home": "CIN",
      "game_time_et": "18:40",
      "game_time_cet": "00:40",
      "date": "2026-03-31",
      "date_display": "wo 1 apr",
      "starter_away": "Bubba Chandler",
      "starter_home": "Brandon Williamson",
      "watch_status": "nacht",
      "is_mine": false,
      "my_team": null
    },
    {
      "away": "WSH",
      "home": "PHI",
      "game_time_et": "18:40",
      "game_time_cet": "00:40",
      "date": "2026-03-31",
      "date_display": "wo 1 apr",
      "starter_away": "TBD",
      "starter_home": "Andrew Painter",
      "watch_status": "nacht",
      "is_mine": false,
      "my_team": null
    },
    {
      "away": "CWS",
      "home": "MIA",
      "game_time_et": "18:40",
      "game_time_cet": "00:40",
      "date": "2026-03-31",
      "date_display": "wo 1 apr",
      "starter_away": "Erick Fedde",
      "starter_home": "Janson Junk",
      "watch_status": "nacht",
      "is_mine": false,
      "my_team": null
    },
    {
      "away": "COL",
      "home": "TOR",
      "game_time_et": "19:07",
      "game_time_cet": "01:07",
      "date": "2026-03-31",
      "date_display": "wo 1 apr",
      "starter_away": "TBD",
      "starter_home": "Max Scherzer",
      "watch_status": "nacht",
      "is_mine": false,
      "my_team": null
    },
    {
      "away": "ATH",
      "home": "ATL",
      "game_time_et": "19:15",
      "game_time_cet": "01:15",
      "date": "2026-03-31",
      "date_display": "wo 1 apr",
      "starter_away": "TBD",
      "starter_home": "TBD",
      "watch_status": "nacht",
      "is_mine": false,
      "my_team": null
    },
    {
      "away": "LAA",
      "home": "CHC",
      "game_time_et": "19:40",
      "game_time_cet": "01:40",
      "date": "2026-03-31",
      "date_display": "wo 1 apr",
      "starter_away": "TBD",
      "starter_home": "TBD",
      "watch_status": "nacht",
      "is_mine": false,
      "my_team": null
    },
    {
      "away": "TB",
      "home": "MIL",
      "game_time_et": "19:40",
      "game_time_cet": "01:40",
      "date": "2026-03-31",
      "date_display": "wo 1 apr",
      "starter_away": "Shane McClanahan",
      "starter_home": "Brandon Woodruff",
      "watch_status": "nacht",
      "is_mine": true,
      "my_team": "TB"
    },
    {
      "away": "NYM",
      "home": "STL",
      "game_time_et": "19:45",
      "game_time_cet": "01:45",
      "date": "2026-03-31",
      "date_display": "wo 1 apr",
      "starter_away": "Kodai Senga",
      "starter_home": "Andre Pallante",
      "watch_status": "nacht",
      "is_mine": true,
      "my_team": "NYM"
    },
    {
      "away": "BOS",
      "home": "HOU",
      "game_time_et": "20:10",
      "game_time_cet": "02:10",
      "date": "2026-03-31",
      "date_display": "wo 1 apr",
      "starter_away": "Brayan Bello",
      "starter_home": "TBD",
      "watch_status": "nacht",
      "is_mine": false,
      "my_team": null
    },
    {
      "away": "DET",
      "home": "AZ",
      "game_time_et": "21:40",
      "game_time_cet": "03:40",
      "date": "2026-03-31",
      "date_display": "wo 1 apr",
      "starter_away": "Casey Mize",
      "starter_home": "Brandon Pfaadt",
      "watch_status": "nacht",
      "is_mine": false,
      "my_team": null
    },
    {
      "away": "SF",
      "home": "SD",
      "game_time_et": "21:40",
      "game_time_cet": "03:40",
      "date": "2026-03-31",
      "date_display": "wo 1 apr",
      "starter_away": "TBD",
      "starter_home": "TBD",
      "watch_status": "nacht",
      "is_mine": false,
      "my_team": null
    },
    {
      "away": "NYY",
      "home": "SEA",
      "game_time_et": "21:40",
      "game_time_cet": "03:40",
      "date": "2026-03-31",
      "date_display": "wo 1 apr",
      "starter_away": "TBD",
      "starter_home": "Logan Gilbert",
      "watch_status": "nacht",
      "is_mine": false,
      "my_team": null
    },
    {
      "away": "CLE",
      "home": "LAD",
      "game_time_et": "22:10",
      "game_time_cet": "04:10",
      "date": "2026-03-31",
      "date_display": "wo 1 apr",
      "starter_away": "TBD",
      "starter_home": "Shohei Ohtani",
      "watch_status": "nacht",
      "is_mine": false,
      "my_team": null
    },
    {
      "away": "ATH",
      "home": "ATL",
      "game_time_et": "12:15",
      "game_time_cet": "18:15",
      "date": "2026-04-01",
      "date_display": "wo 1 apr",
      "starter_away": "TBD",
      "starter_home": "TBD",
      "watch_status": "kijkbaar",
      "is_mine": false,
      "my_team": null
    },
    {
      "away": "TEX",
      "home": "BAL",
      "game_time_et": "12:35",
      "game_time_cet": "18:35",
      "date": "2026-04-01",
      "date_display": "wo 1 apr",
      "starter_away": "TBD",
      "starter_home": "TBD",
      "watch_status": "kijkbaar",
      "is_mine": false,
      "my_team": null
    },
    {
      "away": "PIT",
      "home": "CIN",
      "game_time_et": "12:40",
      "game_time_cet": "18:40",
      "date": "2026-04-01",
      "date_display": "wo 1 apr",
      "starter_away": "TBD",
      "starter_home": "TBD",
      "watch_status": "kijkbaar",
      "is_mine": false,
      "my_team": null
    },
    {
      "away": "WSH",
      "home": "PHI",
      "game_time_et": "13:05",
      "game_time_cet": "19:05",
      "date": "2026-04-01",
      "date_display": "wo 1 apr",
      "starter_away": "TBD",
      "starter_home": "TBD",
      "watch_status": "kijkbaar",
      "is_mine": false,
      "my_team": null
    },
    {
      "away": "COL",
      "home": "TOR",
      "game_time_et": "13:07",
      "game_time_cet": "19:07",
      "date": "2026-04-01",
      "date_display": "wo 1 apr",
      "starter_away": "TBD",
      "starter_home": "TBD",
      "watch_status": "kijkbaar",
      "is_mine": false,
      "my_team": null
    },
    {
      "away": "CWS",
      "home": "MIA",
      "game_time_et": "13:10",
      "game_time_cet": "19:10",
      "date": "2026-04-01",
      "date_display": "wo 1 apr",
      "starter_away": "Shane Smith",
      "starter_home": "TBD",
      "watch_status": "kijkbaar",
      "is_mine": false,
      "my_team": null
    },
    {
      "away": "NYM",
      "home": "STL",
      "game_time_et": "13:15",
      "game_time_cet": "19:15",
      "date": "2026-04-01",
      "date_display": "wo 1 apr",
      "starter_away": "TBD",
      "starter_home": "TBD",
      "watch_status": "kijkbaar",
      "is_mine": true,
      "my_team": "NYM"
    },
    {
      "away": "TB",
      "home": "MIL",
      "game_time_et": "13:40",
      "game_time_cet": "19:40",
      "date": "2026-04-01",
      "date_display": "wo 1 apr",
      "starter_away": "TBD",
      "starter_home": "Jacob Misiorowski",
      "watch_status": "kijkbaar",
      "is_mine": true,
      "my_team": "TB"
    },
    {
      "away": "BOS",
      "home": "HOU",
      "game_time_et": "14:10",
      "game_time_cet": "20:10",
      "date": "2026-04-01",
      "date_display": "wo 1 apr",
      "starter_away": "Garrett Crochet",
      "starter_home": "TBD",
      "watch_status": "kijkbaar",
      "is_mine": false,
      "my_team": null
    },
    {
      "away": "LAA",
      "home": "CHC",
      "game_time_et": "14:20",
      "game_time_cet": "20:20",
      "date": "2026-04-01",
      "date_display": "wo 1 apr",
      "starter_away": "TBD",
      "starter_home": "TBD",
      "watch_status": "kijkbaar",
      "is_mine": false,
      "my_team": null
    },
    {
      "away": "DET",
      "home": "AZ",
      "game_time_et": "15:40",
      "game_time_cet": "21:40",
      "date": "2026-04-01",
      "date_display": "wo 1 apr",
      "starter_away": "TBD",
      "starter_home": "Zac Gallen",
      "watch_status": "nacht",
      "is_mine": false,
      "my_team": null
    },
    {
      "away": "SF",
      "home": "SD",
      "game_time_et": "16:10",
      "game_time_cet": "22:10",
      "date": "2026-04-01",
      "date_display": "wo 1 apr",
      "starter_away": "TBD",
      "starter_home": "Nick Pivetta",
      "watch_status": "nacht",
      "is_mine": false,
      "my_team": null
    },
    {
      "away": "NYY",
      "home": "SEA",
      "game_time_et": "16:10",
      "game_time_cet": "22:10",
      "date": "2026-04-01",
      "date_display": "wo 1 apr",
      "starter_away": "TBD",
      "starter_home": "TBD",
      "watch_status": "nacht",
      "is_mine": false,
      "my_team": null
    },
    {
      "away": "MIN",
      "home": "KC",
      "game_time_et": "19:40",
      "game_time_cet": "01:40",
      "date": "2026-04-01",
      "date_display": "do 2 apr",
      "starter_away": "TBD",
      "starter_home": "Noah Cameron",
      "watch_status": "nacht",
      "is_mine": false,
      "my_team": null
    },
    {
      "away": "CLE",
      "home": "LAD",
      "game_time_et": "20:20",
      "game_time_cet": "02:20",
      "date": "2026-04-01",
      "date_display": "do 2 apr",
      "starter_away": "TBD",
      "starter_home": "TBD",
      "watch_status": "nacht",
      "is_mine": false,
      "my_team": null
    },
    {
      "away": "MIN",
      "home": "KC",
      "game_time_et": "14:10",
      "game_time_cet": "20:10",
      "date": "2026-04-02",
      "date_display": "do 2 apr",
      "starter_away": "TBD",
      "starter_home": "TBD",
      "watch_status": "kijkbaar",
      "is_mine": false,
      "my_team": null
    },
    {
      "away": "TOR",
      "home": "CWS",
      "game_time_et": "16:10",
      "game_time_cet": "22:10",
      "date": "2026-04-02",
      "date_display": "do 2 apr",
      "starter_away": "TBD",
      "starter_home": "TBD",
      "watch_status": "nacht",
      "is_mine": false,
      "my_team": null
    },
    {
      "away": "ATL",
      "home": "AZ",
      "game_time_et": "21:40",
      "game_time_cet": "03:40",
      "date": "2026-04-02",
      "date_display": "vr 3 apr",
      "starter_away": "TBD",
      "starter_home": "TBD",
      "watch_status": "nacht",
      "is_mine": false,
      "my_team": null
    },
    {
      "away": "NYM",
      "home": "SF",
      "game_time_et": "21:45",
      "game_time_cet": "03:45",
      "date": "2026-04-02",
      "date_display": "vr 3 apr",
      "starter_away": "TBD",
      "starter_home": "TBD",
      "watch_status": "nacht",
      "is_mine": true,
      "my_team": "NYM"
    },
    {
      "away": "LAD",
      "home": "WSH",
      "game_time_et": "13:05",
      "game_time_cet": "19:05",
      "date": "2026-04-03",
      "date_display": "vr 3 apr",
      "starter_away": "TBD",
      "starter_home": "TBD",
      "watch_status": "kijkbaar",
      "is_mine": false,
      "my_team": null
    },
    {
      "away": "STL",
      "home": "DET",
      "game_time_et": "13:10",
      "game_time_cet": "19:10",
      "date": "2026-04-03",
      "date_display": "vr 3 apr",
      "starter_away": "TBD",
      "starter_home": "TBD",
      "watch_status": "kijkbaar",
      "is_mine": false,
      "my_team": null
    },
    {
      "away": "MIA",
      "home": "NYY",
      "game_time_et": "13:35",
      "game_time_cet": "19:35",
      "date": "2026-04-03",
      "date_display": "vr 3 apr",
      "starter_away": "TBD",
      "starter_home": "TBD",
      "watch_status": "kijkbaar",
      "is_mine": false,
      "my_team": null
    },
    {
      "away": "SD",
      "home": "BOS",
      "game_time_et": "14:10",
      "game_time_cet": "20:10",
      "date": "2026-04-03",
      "date_display": "vr 3 apr",
      "starter_away": "TBD",
      "starter_home": "TBD",
      "watch_status": "kijkbaar",
      "is_mine": false,
      "my_team": null
    },
    {
      "away": "CIN",
      "home": "TEX",
      "game_time_et": "16:05",
      "game_time_cet": "22:05",
      "date": "2026-04-03",
      "date_display": "vr 3 apr",
      "starter_away": "TBD",
      "starter_home": "TBD",
      "watch_status": "nacht",
      "is_mine": false,
      "my_team": null
    },
    {
      "away": "CHC",
      "home": "CLE",
      "game_time_et": "16:10",
      "game_time_cet": "22:10",
      "date": "2026-04-03",
      "date_display": "vr 3 apr",
      "starter_away": "TBD",
      "starter_home": "TBD",
      "watch_status": "nacht",
      "is_mine": false,
      "my_team": null
    },
    {
      "away": "TB",
      "home": "MIN",
      "game_time_et": "16:10",
      "game_time_cet": "22:10",
      "date": "2026-04-03",
      "date_display": "vr 3 apr",
      "starter_away": "TBD",
      "starter_home": "TBD",
      "watch_status": "nacht",
      "is_mine": true,
      "my_team": "TB"
    },
    {
      "away": "PHI",
      "home": "COL",
      "game_time_et": "16:10",
      "game_time_cet": "22:10",
      "date": "2026-04-03",
      "date_display": "vr 3 apr",
      "starter_away": "TBD",
      "starter_home": "TBD",
      "watch_status": "nacht",
      "is_mine": false,
      "my_team": null
    },
    {
      "away": "BAL",
      "home": "PIT",
      "game_time_et": "16:12",
      "game_time_cet": "22:12",
      "date": "2026-04-03",
      "date_display": "vr 3 apr",
      "starter_away": "TBD",
      "starter_home": "TBD",
      "watch_status": "nacht",
      "is_mine": false,
      "my_team": null
    },
    {
      "away": "MIL",
      "home": "KC",
      "game_time_et": "19:45",
      "game_time_cet": "01:45",
      "date": "2026-04-03",
      "date_display": "za 4 apr",
      "starter_away": "TBD",
      "starter_home": "TBD",
      "watch_status": "nacht",
      "is_mine": false,
      "my_team": null
    },
    {
      "away": "SEA",
      "home": "LAA",
      "game_time_et": "21:38",
      "game_time_cet": "03:38",
      "date": "2026-04-03",
      "date_display": "za 4 apr",
      "starter_away": "TBD",
      "starter_home": "TBD",
      "watch_status": "nacht",
      "is_mine": false,
      "my_team": null
    },
    {
      "away": "HOU",
      "home": "ATH",
      "game_time_et": "21:40",
      "game_time_cet": "03:40",
      "date": "2026-04-03",
      "date_display": "za 4 apr",
      "starter_away": "TBD",
      "starter_home": "TBD",
      "watch_status": "nacht",
      "is_mine": false,
      "my_team": null
    },
    {
      "away": "ATL",
      "home": "AZ",
      "game_time_et": "21:45",
      "game_time_cet": "03:45",
      "date": "2026-04-03",
      "date_display": "za 4 apr",
      "starter_away": "TBD",
      "starter_home": "TBD",
      "watch_status": "nacht",
      "is_mine": false,
      "my_team": null
    },
    {
      "away": "NYM",
      "home": "SF",
      "game_time_et": "22:15",
      "game_time_cet": "04:15",
      "date": "2026-04-03",
      "date_display": "za 4 apr",
      "starter_away": "TBD",
      "starter_home": "TBD",
      "watch_status": "nacht",
      "is_mine": true,
      "my_team": "NYM"
    }
  ]
}